flapison/__init__.py
flapison/api.py
flapison/content.py
flapison/decorators.py
flapison/errors.py
flapison/exceptions.py
flapison/pagination.py
flapison/querystring.py
flapison/resource.py
flapison/schema.py
flapison/utils.py
flapison/data_layers/__init__.py
flapison/data_layers/alchemy.py
flapison/data_layers/base.py
flapison/data_layers/filtering/__init__.py
flapison/data_layers/filtering/alchemy.py
flask_rest_jsonapi/__init__.py
flask_rest_jsonapi/api.py
flask_rest_jsonapi/content.py
flask_rest_jsonapi/decorators.py
flask_rest_jsonapi/errors.py
flask_rest_jsonapi/exceptions.py
flask_rest_jsonapi/pagination.py
flask_rest_jsonapi/querystring.py
flask_rest_jsonapi/resource.py
flask_rest_jsonapi/schema.py
flask_rest_jsonapi/utils.py
flask_rest_jsonapi/data_layers/__init__.py
flask_rest_jsonapi/data_layers/alchemy.py
flask_rest_jsonapi/data_layers/base.py
flask_rest_jsonapi/data_layers/filtering/__init__.py
flask_rest_jsonapi/data_layers/filtering/alchemy.py
flapison-0.30.10.dist-info/LICENSE
flapison-0.30.10.dist-info/METADATA
flapison-0.30.10.dist-info/WHEEL
flapison-0.30.10.dist-info/top_level.txt
flapison-0.30.10.dist-info/RECORD
