Metadata-Version: 2.1
Name: flapison
Version: 0.30.10
Summary: Flask extension to create REST web api according to JSONAPI 1.0 specification with Flask, Marshmallow                  and data provider of your choice (SQLAlchemy, MongoDB, ...)
Home-page: https://github.com/TMiguelT/flapison
Author: Michael Milton
Author-email: ttmigueltt@gmail.com
License: MIT
Keywords: web api rest jsonapi flask sqlalchemy marshmallow
Platform: any
Classifier: Framework :: Flask
Classifier: Programming Language :: Python :: 3
Classifier: Programming Language :: Python :: 3.6
Classifier: Programming Language :: Python :: 3.7
Classifier: Programming Language :: Python :: 3.8
Classifier: License :: OSI Approved :: MIT License
Requires-Dist: Flask (>=0.11)
Requires-Dist: marshmallow (>=3.1.0)
Requires-Dist: marshmallow-jsonapi (>=0.22.0)
Requires-Dist: six
Requires-Dist: sqlalchemy
Provides-Extra: dev
Requires-Dist: coverage ; extra == 'dev'
Requires-Dist: coveralls ; extra == 'dev'
Requires-Dist: pytest ; extra == 'dev'
Provides-Extra: docs
Requires-Dist: sphinx ; extra == 'docs'
